imobiliar/__init__.py
imobiliar/auth.py
imobiliar/exec.py
imobiliar/s3_client.py
imobiliar/api/__init__.py
imobiliar/api/condominos.py
imobiliar/api/contas_pagar.py
imobiliar-1.0.9.dist-info/licenses/LICENSE
imobiliar-1.0.9.dist-info/METADATA
imobiliar-1.0.9.dist-info/WHEEL
imobiliar-1.0.9.dist-info/top_level.txt
imobiliar-1.0.9.dist-info/RECORD
