Metadata-Version: 2.4
Name: imobiliar
Version: 1.0.9
Summary: Biblioteca para automações e integrações de sistemas imobiliários
Home-page: https://pypi.org/project/imobiliar/
Author: Christian Schmitz
Author-email: Christian Schmitz <christian.barbosa@creditoreal.com.br>
License: MIT License
Project-URL: Homepage, https://pypi.org/project/imobiliar/
Project-URL: Source, https://github.com/seuusuario/imobiliar
Classifier: Programming Language :: Python :: 3
Requires-Python: >=3.9
License-File: LICENSE
Requires-Dist: boto3
Requires-Dist: requests
Dynamic: license-file
